gsat/__init__.py
gsat/build_db.py
gsat/find_adapter.py
gsat/input_validation.py
gsat/mature.py
gsat/summarize_library.py
gsat/trim_adapter.py
gsat/writeShiny.py
gsat-0.1.data/scripts/gsat
gsat-0.1.dist-info/LICENSE.txt
gsat-0.1.dist-info/METADATA
gsat-0.1.dist-info/WHEEL
gsat-0.1.dist-info/top_level.txt
gsat-0.1.dist-info/RECORD
