Metadata-Version: 2.1
Name: gsat
Version: 0.1
Summary: General Small RNA-seq Analysis Tool
Home-page: https://github.com/MikeAxtell/gsat
Author: Michael J. Axtell
Author-email: mja18@psu.edu
License: UNKNOWN
Platform: UNKNOWN
Classifier: Programming Language :: Python :: 3
Classifier: License :: OSI Approved :: MIT License
Classifier: Operating System :: OS Independent
Requires-Python: >3.5, <4
Requires-Dist: biopython
Requires-Dist: python-Levenshtein
